busnearby/__init__.py
busnearby-0.1.3.dist-info/LICENSE
busnearby-0.1.3.dist-info/METADATA
busnearby-0.1.3.dist-info/WHEEL
busnearby-0.1.3.dist-info/top_level.txt
busnearby-0.1.3.dist-info/RECORD
